<?xml version="1.0" encoding="utf-8" standalone="yes"?>
<post>
  <author>andrej</author>
  <title>Gender: Web Developer vs. Web Developer</title>
  <description />
  <content>&lt;iframe height="281" src="http://player.vimeo.com/video/20504845" frameborder="0" width="500"&gt;&lt;/iframe&gt;  &lt;p&gt;&lt;a href="http://vimeo.com/20504845"&gt;Web Developers vs Web Developers&lt;/a&gt; from &lt;a href="http://vimeo.com/user3009668"&gt;Cassie McDaniel&lt;/a&gt; on &lt;a href="http://vimeo.com"&gt;Vimeo&lt;/a&gt;.&lt;/p&gt;  &lt;p&gt;I love the role the designer plays in this video :)&lt;/p&gt;  &lt;p&gt;[via &lt;a href="http://graphic.is/videos/female-web-developers-vs-male-web-developers/" target="_blank"&gt;graphic.is&lt;/a&gt;]&lt;/p&gt;</content>
  <ispublished>True</ispublished>
  <isdeleted>False</isdeleted>
  <iscommentsenabled>True</iscommentsenabled>
  <pubDate>2011-03-10 14:54:39</pubDate>
  <lastModified>2011-03-10 14:55:57</lastModified>
  <raters>0</raters>
  <rating>0</rating>
  <slug>Web-Developer-vs-Web-Developer</slug>
  <tags>
    <tag>video</tag>
    <tag>fun</tag>
  </tags>
  <comments />
  <categories>
    <category>9c2910dd-8a70-451f-b9d5-0ec47609aedb</category>
  </categories>
  <notifications />
</post>